odoo/addons/dms_storage/README.rst
odoo/addons/dms_storage/__init__.py
odoo/addons/dms_storage/__manifest__.py
odoo/addons/dms_storage/i18n/dms_storage.pot
odoo/addons/dms_storage/models/__init__.py
odoo/addons/dms_storage/models/dms_file.py
odoo/addons/dms_storage/models/dms_storage.py
odoo/addons/dms_storage/readme/CONTRIBUTORS.rst
odoo/addons/dms_storage/readme/DESCRIPTION.rst
odoo/addons/dms_storage/static/description/icon.png
odoo/addons/dms_storage/static/description/index.html
odoo/addons/dms_storage/tests/__init__.py
odoo/addons/dms_storage/tests/test_storage.py
odoo/addons/dms_storage/views/dms_storage.xml
odoo14_addon_dms_storage-14.0.1.0.1.dist-info/METADATA
odoo14_addon_dms_storage-14.0.1.0.1.dist-info/WHEEL
odoo14_addon_dms_storage-14.0.1.0.1.dist-info/top_level.txt
odoo14_addon_dms_storage-14.0.1.0.1.dist-info/RECORD
